webgrid/__init__.py
webgrid/blazeweb.py
webgrid/extensions.py
webgrid/filters.py
webgrid/flask.py
webgrid/renderers.py
webgrid/testing.py
webgrid/types.py
webgrid/utils.py
webgrid/validators.py
webgrid/version.py
webgrid/i18n/babel.cfg
webgrid/i18n/webgrid.pot
webgrid/i18n/es/LC_MESSAGES/webgrid.mo
webgrid/i18n/es/LC_MESSAGES/webgrid.po
webgrid/static/application_form_edit.png
webgrid/static/b_firstpage.png
webgrid/static/b_lastpage.png
webgrid/static/b_nextpage.png
webgrid/static/b_prevpage.png
webgrid/static/bd_firstpage.png
webgrid/static/bd_lastpage.png
webgrid/static/bd_nextpage.png
webgrid/static/bd_prevpage.png
webgrid/static/delete.png
webgrid/static/gettext.min.js
webgrid/static/jquery.multiple.select.js
webgrid/static/multiple-select.css
webgrid/static/multiple-select.png
webgrid/static/th_arrow_down.png
webgrid/static/th_arrow_up.png
webgrid/static/webgrid.css
webgrid/static/webgrid.js
webgrid/static/i18n/es/LC_MESSAGES/webgrid.json
webgrid/templates/grid.html
webgrid/templates/grid_footer.html
webgrid/templates/grid_header.html
webgrid/templates/grid_table.html
webgrid/templates/header_filtering.html
webgrid/templates/header_paging.html
webgrid/templates/header_sorting.html
webgrid-0.20250807.2.dist-info/METADATA
webgrid-0.20250807.2.dist-info/WHEEL
webgrid-0.20250807.2.dist-info/RECORD
