Metadata-Version: 2.4
Name: WebGrid
Version: 0.20250807.2
Summary: A library for rendering HTML tables and Excel files from SQLAlchemy models.
Project-URL: homepage, https://github.com/level12/webgrid
Author-email: Level 12 <devteam@level12.io>
License: Copyright (c) 2014 by Randy Syring and contributors.
Classifier: Development Status :: 4 - Beta
Classifier: Intended Audience :: Developers
Classifier: License :: OSI Approved :: BSD License
Classifier: Operating System :: OS Independent
Requires-Python: >=3.10
Requires-Dist: blazeutils>=0.6.0
Requires-Dist: jinja2
Requires-Dist: python-dateutil
Requires-Dist: sqlalchemy>=1.4.20
Requires-Dist: werkzeug
Provides-Extra: i18n
Requires-Dist: morphi; extra == 'i18n'
